{
    "client": "Thunder Client",
    "collectionName": "User",
    "dateExported": "2024-03-07T06:49:16.208Z",
    "version": "1.1",
    "folders": [],
    "requests": [
        {
            "_id": "ef6681ff-8c0f-4980-a0cd-4e84038d0a7f",
            "colId": "ad268604-63d4-4ba8-8239-20465e858bde",
            "containerId": "",
            "name": "userPost",
            "url": "http://localhost:10433/tellMe/v1/user/",
            "method": "POST",
            "sortNum": 2500,
            "created": "2024-03-05T05:26:33.079Z",
            "modified": "2024-03-05T05:26:33.079Z",
            "headers": [],
            "params": [],
            "body": {
                "type": "json",
                "raw": "{\n  \"name\":\"user\",\n  \"mail\":\"user1@kinal.edu.gt\",\n  \"password\":\"uss\"\n}",
                "form": []
            },
            "tests": []
        },
        {
            "_id": "12d7d9fa-a61c-4cbb-b8cd-716e86061c52",
            "colId": "ad268604-63d4-4ba8-8239-20465e858bde",
            "containerId": "",
            "name": "editMyProfile Copy Copy",
            "url": "http://localhost:10433/academic/user/editMyProfile",
            "method": "PUT",
            "sortNum": 17500,
            "created": "2024-02-18T06:19:48.082Z",
            "modified": "2024-02-18T06:19:48.082Z",
            "headers": [
                {
                    "name": "x-access-token",
                    "value": "eyJhbGciOiJIUzI1NiIsInR5cCI6IkpXVCJ9.eyJ1aWQiOiI2NWNkNjQyNmMwMjg2NmI5NzZhZjgyOTUiLCJpYXQiOjE3MDgyMzYwNjMsImV4cCI6MTcwODIzOTY2M30.rRQ23yszT2xP48CdBcTupihIqRe0x5LMw3GwaJB6AhY"
                }
            ],
            "params": [],
            "body": {
                "type": "json",
                "raw": "{\n  \"nombre\":\"Braulio Echeverria\"\n}",
                "form": []
            },
            "tests": []
        }
    ]
}